fin_common/__init__.py
fin_common/llm_util.py
fin_common/yfinance_service.py
fin_common/database/utils.py
fin_common/technical_anslysis/analysis.py
fin_common/technical_anslysis/analysis_type.py
fin_common/technical_anslysis/liquidity.py
fin_common/technical_anslysis/momentum.py
fin_common/technical_anslysis/pattern.py
fin_common/technical_anslysis/util.py
fin_common/technical_anslysis/volatility.py
fin_common-0.2.6.dist-info/METADATA
fin_common-0.2.6.dist-info/WHEEL
fin_common-0.2.6.dist-info/top_level.txt
fin_common-0.2.6.dist-info/RECORD
