Metadata-Version: 2.2
Name: fin-common
Version: 0.2.6
Summary: A shared common module for FinForAll services.
Author-email: Tommy Pang <tommypang04@gmail.com>
License: MIT
Requires-Python: >=3.10
